jwtjwkhelper/__init__.py
jwtjwkhelper/jwtjwkhelper.py
jwtjwkhelper/py.typed
jwtjwkhelper-0.0.10.dist-info/METADATA
jwtjwkhelper-0.0.10.dist-info/WHEEL
jwtjwkhelper-0.0.10.dist-info/licenses/LICENSE.md
jwtjwkhelper-0.0.10.dist-info/RECORD
