Metadata-Version: 2.4
Name: jwtjwkhelper
Version: 0.0.10
Summary: JWTJWKHelper
Project-URL: Homepage, https://github.com/vroomfondel/jwtjwkhelper
Project-URL: Repository, https://github.com/vroomfondel/jwtjwkhelper
Project-URL: Issues, https://github.com/vroomfondel/jwtjwkhelper/issues
Author-email: Henning Thieß <ht@xomox.cc>
License-File: LICENSE.md
Keywords: authentication,cryptography,json web key,json web token,jwk,jwt,private key,public key,security,token
Classifier: Development Status :: 5 - Production/Stable
Classifier: License :: OSI Approved :: MIT License
Classifier: Operating System :: OS Independent
Classifier: Programming Language :: Python :: 3
Classifier: Programming Language :: Python :: 3.14
Classifier: Topic :: Internet
Classifier: Topic :: Internet :: WWW/HTTP :: Session
Classifier: Topic :: Software Development :: Libraries
Classifier: Topic :: Software Development :: Libraries :: Python Modules
Requires-Python: >=3.12
Requires-Dist: jwcrypto>=1.5.6
Requires-Dist: loguru>=0.7.3
Requires-Dist: pyjwt>=2.10.1
Requires-Dist: pytz>=2025.2
